streamlit_chat_widget/__init__.py
streamlit_chat_widget/frontend/build/asset-manifest.json
streamlit_chat_widget/frontend/build/bootstrap.min.css
streamlit_chat_widget/frontend/build/index.html
streamlit_chat_widget/frontend/build/static/css/main.8d240626.css
streamlit_chat_widget/frontend/build/static/css/main.8d240626.css.map
streamlit_chat_widget/frontend/build/static/js/main.5d5fa7e9.js
streamlit_chat_widget/frontend/build/static/js/main.5d5fa7e9.js.LICENSE.txt
streamlit_chat_widget/frontend/build/static/js/main.5d5fa7e9.js.map
streamlit_chat_widget/frontend/build/static/js/main.67dcf417.js
streamlit_chat_widget/frontend/build/static/js/main.67dcf417.js.LICENSE.txt
streamlit_chat_widget/frontend/build/static/js/main.67dcf417.js.map
streamlit_chat_widget/frontend/build/static/js/main.84e8fb8e.js
streamlit_chat_widget/frontend/build/static/js/main.84e8fb8e.js.LICENSE.txt
streamlit_chat_widget/frontend/build/static/js/main.84e8fb8e.js.map
streamlit_chat_widget_franklu-0.6.0.dist-info/licenses/LICENSE
streamlit_chat_widget_franklu-0.6.0.dist-info/METADATA
streamlit_chat_widget_franklu-0.6.0.dist-info/WHEEL
streamlit_chat_widget_franklu-0.6.0.dist-info/top_level.txt
streamlit_chat_widget_franklu-0.6.0.dist-info/RECORD
