Metadata-Version: 2.4
Name: streamlit_chat_widget_franklu
Version: 0.6.0
Summary: A custom chat input widget for Streamlit based on Mohammed Bahageel's Chat Input Widget
Home-page: https://github.com/franklu2014/Chat_input_widget
Author: Frank Lu
Author-email: franklu@live.ca
Classifier: Programming Language :: Python :: 3
Classifier: License :: OSI Approved :: MIT License
Classifier: Operating System :: OS Independent
Requires-Python: >=3.6
License-File: LICENSE
Requires-Dist: streamlit>=1.0
Dynamic: author
Dynamic: author-email
Dynamic: classifier
Dynamic: description
Dynamic: description-content-type
Dynamic: home-page
Dynamic: license-file
Dynamic: requires-dist
Dynamic: requires-python
Dynamic: summary
